Workbook

Sheet 前提
A1: VISUAL LABO｜3年収益計画シミュレーション（ToB：機械リース＋専用ジェル）
A2: 青字＝入力レバー（変更で全再計算）／黄色＝主要レバー
A4: ◤ ジェル 単価・原価（粗利は税抜同士）
A5: ジェル卸価格（税抜） | B5: 4800 | C5: サロンへの卸単価。基準
A6: ジェル卸価格（税込10%） | B6: =B5*1.1 -> 5280 | C6: 税抜×1.1（＝¥5,280）
A7: OEM原価・1,000本ロット（税抜） | B7: 1800
A8: OEM原価・500本ロット（税抜/参考） | B8: 2100
A9: 採用原価（大量発注） | B9: =B7 -> 1800
A10: 粗利／本（税抜） | B10: =B5-B9 -> 3000
A11: 粗利率 | B11: =B10/B5 -> 0.625
A13: ◤ ジェル 消費前提
A14: 1本あたり容量（ml） | B14: 750 | C14: 750〜800ml。控えめに750で試算
A15: 1施術あたり使用量（ml） | B15: 30 | C15: 60分施術で約30ml
A16: 1本あたり施術回数 | B16: =B14/B15 -> 25 | C16: 容量÷使用量（＝25回）
A18: ◤ 機械・契約（ToB／リース基本）
A19: 初期費用／台（契約時・別途） | B19: 330000 | C19: 導入費（設置/初期設定/研修）。リースとは別・一度きり
A20: 月額リース／台 | B20: 55000 | C20: 7カ月目〜課金（初期費用充当後）
A21: リース課金開始月（各台） | B21: 1 | C21: 契約時（1カ月目）から課金。初期費用は別途
A22: ジェル無償サービス（契約時）本数/台 | B22: 1 | C22: 販促。コスト＝原価×本数
A23: 機械原価／台（任意・リース粗利算定用） | B23: 0 | C23: 分かれば入力。0ならリース＝ほぼ粗利として表示
A25: ◤ 稼働・導入計画（3年で1,000台）
A26: 採用稼働（施術回数/月/台） | B26: 88 | C26: 標準=88（4回/日×22日）。控えめ44／高稼働200
A27: 1年目 導入台数（台/年） | B27: 240
A28: 2年目 導入台数（台/年） | B28: 360
A29: 3年目 導入台数（台/年） | B29: 400 | C29: 3年累計＝1,000台
A30: 3年累計 導入台数 | B30: =B27+B28+B29 -> 1000
A33: ◤ 稼働シナリオ（1台あたり月次）
A34: シナリオ | B34: 回/日 | C34: 稼働日/月 | D34: 施術回数/月 | E34: 消費本数/月 | F34: ジェル売上/月 | G34: ジェル粗利/月
A35: 控えめ | B35: 2 | C35: 22 | D35: =B35*C35 -> 44 | E35: =D35*$B$15/$B$14 -> 1.76 | F35: =E35*$B$5 -> 8448 | G35: =E35*$B$10 -> 5280
A36: 標準（採用） | B36: 4 | C36: 22 | D36: =B36*C36 -> 88 | E36: =D36*$B$15/$B$14 -> 3.52 | F36: =E36*$B$5 -> 16896 | G36: =E36*$B$10 -> 10560
A37: 高稼働 | B37: 8 | C37: 25 | D37: =B37*C37 -> 200 | E37: =D37*$B$15/$B$14 -> 8 | F37: =E37*$B$5 -> 38400 | G37: =E37*$B$10 -> 24000

Sheet 1000台_月間利益
A1: 1,000台フル稼働時の 月間利益構造（定常・全台リース課金）
A2: 対象台数（青字）を変えると再計算。初期費用は新規契約時のみ発生のため定常＝0。
A4: 対象台数 | B4: 1000
A6: シナリオ | B6: 台数 | C6: ジェル消費/月(本) | D6: ジェル売上/月 | E6: ジェル粗利/月 | F6: 機械リース/月 | G6: 月間 ToB売上 | H6: 月間 ToB粗利 | I6: 月間ToB粗利 年換算
A7: 控えめ | B7: =$B$4 -> 1000 | C7: =$B$4*前提!E35 -> 1760 | D7: =$B$4*前提!F35 -> 8448000 | E7: =$B$4*前提!G35 -> 5280000 | F7: =$B$4*前提!$B$20 -> 55000000 | G7: =D7+F7 -> 63448000 | H7: =E7+F7-$B$4*前提!$B$23 -> 60280000 | I7: =H7*12 -> 723360000
A8: 標準 | B8: =$B$4 -> 1000 | C8: =$B$4*前提!E36 -> 3520 | D8: =$B$4*前提!F36 -> 16896000 | E8: =$B$4*前提!G36 -> 10560000 | F8: =$B$4*前提!$B$20 -> 55000000 | G8: =D8+F8 -> 71896000 | H8: =E8+F8-$B$4*前提!$B$23 -> 65560000 | I8: =H8*12 -> 786720000
A9: 高稼働 | B9: =$B$4 -> 1000 | C9: =$B$4*前提!E37 -> 8000 | D9: =$B$4*前提!F37 -> 38400000 | E9: =$B$4*前提!G37 -> 24000000 | F9: =$B$4*前提!$B$20 -> 55000000 | G9: =D9+F9 -> 93400000 | H9: =E9+F9-$B$4*前提!$B$23 -> 79000000 | I9: =H9*12 -> 948000000
A11: ※月間ToB粗利＝ジェル粗利＋機械リース売上−機械原価（機械原価は前提B23、既定0）。固定費（家賃・人件費等）控除前。
A12: ※定常（新規導入停止）想定。もし1,000台到達後も月次で導入継続する場合は 初期費用（=新規台数×¥330,000）が別途上乗せ。

Sheet 3年計画_月次
A1: 3年計画（月次・リース課金は各台7カ月目〜）
A2: 前提の導入台数・稼働・単価を変えると再計算。累計台数は3年目末に1,000台。
A4: 年 | B4: 期末累計台数 | C4: 期末リース課金台数 | D4: 初期費用売上 | E4: リース売上 | F4: ジェル売上 | G4: ジェル粗利 | H4: ToB売上計 | I4: ToB粗利計
A5: 1年目 | B5: =D22 -> 240 | C5: =E22 -> 240 | D5: =SUM(F11:F22) -> 79200000 | E5: =SUM(G11:G22) -> 85800000 | F5: =SUM(J11:J22) -> 26357760 | G5: =SUM(K11:K22) -> 16041600 | H5: =SUM(L11:L22) -> 191357760 | I5: =SUM(M11:M22) -> 181041600
A6: 2年目 | B6: =D34 -> 600 | C6: =E34 -> 600 | D6: =SUM(F23:F34) -> 118800000 | E6: =SUM(G23:G34) -> 287100000 | F6: =SUM(J23:J34) -> 88197120 | G6: =SUM(K23:K34) -> 54475200 | H6: =SUM(L23:L34) -> 494097120 | I6: =SUM(M23:M34) -> 460375200
A7: 3年目 | B7: =D46 -> 1000 | C7: =E46 -> 1000 | D7: =SUM(F35:F46) -> 132000000 | E7: =SUM(G35:G46) -> 539000000 | F7: =SUM(J35:J46) -> 165580800 | G7: =SUM(K35:K46) -> 102768000 | H7: =SUM(L35:L46) -> 836580800 | I7: =SUM(M35:M46) -> 773768000
A10: 月 | B10: 年 | C10: 新規導入 | D10: 累計台数 | E10: リース課金台数 | F10: 初期費用売上 | G10: リース売上 | H10: 施術回数 | I10: 消費本数 | J10: ジェル売上 | K10: ジェル粗利(純) | L10: ToB売上 | M10: ToB粗利
A11: 1 | B11: =IF(A11<=12,1,IF(A11<=24,2,3)) -> 1 | C11: =IF(B11=1,前提!$B$27/12,IF(B11=2,前提!$B$28/12,前提!$B$29/12)) -> 20 | D11: =C11 -> 20 | E11: =D11 -> 20 | F11: =C11*前提!$B$19 -> 6600000 | G11: =E11*前提!$B$20 -> 1100000 | H11: =D11*前提!$B$26 -> 1760 | I11: =H11*前提!$B$15/前提!$B$14 -> 70.4 | J11: =I11*前提!$B$5 -> 337920 | K11: =I11*前提!$B$10-C11*前提!$B$22*前提!$B$7 -> 175200 | L11: =F11+G11+J11 -> 8037920 | M11: =G11+K11+F11-C11*前提!$B$23 -> 7875200
A12: 2 | B12: =IF(A12<=12,1,IF(A12<=24,2,3)) -> 1 | C12: =IF(B12=1,前提!$B$27/12,IF(B12=2,前提!$B$28/12,前提!$B$29/12)) -> 20 | D12: =D11+C12 -> 40 | E12: =D12 -> 40 | F12: =C12*前提!$B$19 -> 6600000 | G12: =E12*前提!$B$20 -> 2200000 | H12: =D12*前提!$B$26 -> 3520 | I12: =H12*前提!$B$15/前提!$B$14 -> 140.8 | J12: =I12*前提!$B$5 -> 675840 | K12: =I12*前提!$B$10-C12*前提!$B$22*前提!$B$7 -> 386400 | L12: =F12+G12+J12 -> 9475840 | M12: =G12+K12+F12-C12*前提!$B$23 -> 9186400
A13: 3 | B13: =IF(A13<=12,1,IF(A13<=24,2,3)) -> 1 | C13: =IF(B13=1,前提!$B$27/12,IF(B13=2,前提!$B$28/12,前提!$B$29/12)) -> 20 | D13: =D12+C13 -> 60 | E13: =D13 -> 60 | F13: =C13*前提!$B$19 -> 6600000 | G13: =E13*前提!$B$20 -> 3300000 | H13: =D13*前提!$B$26 -> 5280 | I13: =H13*前提!$B$15/前提!$B$14 -> 211.2 | J13: =I13*前提!$B$5 -> 1013760 | K13: =I13*前提!$B$10-C13*前提!$B$22*前提!$B$7 -> 597600 | L13: =F13+G13+J13 -> 10913760 | M13: =G13+K13+F13-C13*前提!$B$23 -> 10497600
A14: 4 | B14: =IF(A14<=12,1,IF(A14<=24,2,3)) -> 1 | C14: =IF(B14=1,前提!$B$27/12,IF(B14=2,前提!$B$28/12,前提!$B$29/12)) -> 20 | D14: =D13+C14 -> 80 | E14: =D14 -> 80 | F14: =C14*前提!$B$19 -> 6600000 | G14: =E14*前提!$B$20 -> 4400000 | H14: =D14*前提!$B$26 -> 7040 | I14: =H14*前提!$B$15/前提!$B$14 -> 281.6 | J14: =I14*前提!$B$5 -> 1351680 | K14: =I14*前提!$B$10-C14*前提!$B$22*前提!$B$7 -> 808800 | L14: =F14+G14+J14 -> 12351680 | M14: =G14+K14+F14-C14*前提!$B$23 -> 11808800
A15: 5 | B15: =IF(A15<=12,1,IF(A15<=24,2,3)) -> 1 | C15: =IF(B15=1,前提!$B$27/12,IF(B15=2,前提!$B$28/12,前提!$B$29/12)) -> 20 | D15: =D14+C15 -> 100 | E15: =D15 -> 100 | F15: =C15*前提!$B$19 -> 6600000 | G15: =E15*前提!$B$20 -> 5500000 | H15: =D15*前提!$B$26 -> 8800 | I15: =H15*前提!$B$15/前提!$B$14 -> 352 | J15: =I15*前提!$B$5 -> 1689600 | K15: =I15*前提!$B$10-C15*前提!$B$22*前提!$B$7 -> 1020000 | L15: =F15+G15+J15 -> 13789600 | M15: =G15+K15+F15-C15*前提!$B$23 -> 13120000
A16: 6 | B16: =IF(A16<=12,1,IF(A16<=24,2,3)) -> 1 | C16: =IF(B16=1,前提!$B$27/12,IF(B16=2,前提!$B$28/12,前提!$B$29/12)) -> 20 | D16: =D15+C16 -> 120 | E16: =D16 -> 120 | F16: =C16*前提!$B$19 -> 6600000 | G16: =E16*前提!$B$20 -> 6600000 | H16: =D16*前提!$B$26 -> 10560 | I16: =H16*前提!$B$15/前提!$B$14 -> 422.4 | J16: =I16*前提!$B$5 -> 2027520 | K16: =I16*前提!$B$10-C16*前提!$B$22*前提!$B$7 -> 1231200 | L16: =F16+G16+J16 -> 15227520 | M16: =G16+K16+F16-C16*前提!$B$23 -> 14431200
A17: 7 | B17: =IF(A17<=12,1,IF(A17<=24,2,3)) -> 1 | C17: =IF(B17=1,前提!$B$27/12,IF(B17=2,前提!$B$28/12,前提!$B$29/12)) -> 20 | D17: =D16+C17 -> 140 | E17: =D17 -> 140 | F17: =C17*前提!$B$19 -> 6600000 | G17: =E17*前提!$B$20 -> 7700000 | H17: =D17*前提!$B$26 -> 12320 | I17: =H17*前提!$B$15/前提!$B$14 -> 492.8 | J17: =I17*前提!$B$5 -> 2365440 | K17: =I17*前提!$B$10-C17*前提!$B$22*前提!$B$7 -> 1442400 | L17: =F17+G17+J17 -> 16665440 | M17: =G17+K17+F17-C17*前提!$B$23 -> 15742400
A18: 8 | B18: =IF(A18<=12,1,IF(A18<=24,2,3)) -> 1 | C18: =IF(B18=1,前提!$B$27/12,IF(B18=2,前提!$B$28/12,前提!$B$29/12)) -> 20 | D18: =D17+C18 -> 160 | E18: =D18 -> 160 | F18: =C18*前提!$B$19 -> 6600000 | G18: =E18*前提!$B$20 -> 8800000 | H18: =D18*前提!$B$26 -> 14080 | I18: =H18*前提!$B$15/前提!$B$14 -> 563.2 | J18: =I18*前提!$B$5 -> 2703360 | K18: =I18*前提!$B$10-C18*前提!$B$22*前提!$B$7 -> 1653600 | L18: =F18+G18+J18 -> 18103360 | M18: =G18+K18+F18-C18*前提!$B$23 -> 17053600
A19: 9 | B19: =IF(A19<=12,1,IF(A19<=24,2,3)) -> 1 | C19: =IF(B19=1,前提!$B$27/12,IF(B19=2,前提!$B$28/12,前提!$B$29/12)) -> 20 | D19: =D18+C19 -> 180 | E19: =D19 -> 180 | F19: =C19*前提!$B$19 -> 6600000 | G19: =E19*前提!$B$20 -> 9900000 | H19: =D19*前提!$B$26 -> 15840 | I19: =H19*前提!$B$15/前提!$B$14 -> 633.6 | J19: =I19*前提!$B$5 -> 3041280 | K19: =I19*前提!$B$10-C19*前提!$B$22*前提!$B$7 -> 1864800 | L19: =F19+G19+J19 -> 19541280 | M19: =G19+K19+F19-C19*前提!$B$23 -> 18364800
A20: 10 | B20: =IF(A20<=12,1,IF(A20<=24,2,3)) -> 1 | C20: =IF(B20=1,前提!$B$27/12,IF(B20=2,前提!$B$28/12,前提!$B$29/12)) -> 20 | D20: =D19+C20 -> 200 | E20: =D20 -> 200 | F20: =C20*前提!$B$19 -> 6600000 | G20: =E20*前提!$B$20 -> 11000000 | H20: =D20*前提!$B$26 -> 17600 | I20: =H20*前提!$B$15/前提!$B$14 -> 704 | J20: =I20*前提!$B$5 -> 3379200 | K20: =I20*前提!$B$10-C20*前提!$B$22*前提!$B$7 -> 2076000 | L20: =F20+G20+J20 -> 20979200 | M20: =G20+K20+F20-C20*前提!$B$23 -> 19676000
A21: 11 | B21: =IF(A21<=12,1,IF(A21<=24,2,3)) -> 1 | C21: =IF(B21=1,前提!$B$27/12,IF(B21=2,前提!$B$28/12,前提!$B$29/12)) -> 20 | D21: =D20+C21 -> 220 | E21: =D21 -> 220 | F21: =C21*前提!$B$19 -> 6600000 | G21: =E21*前提!$B$20 -> 12100000 | H21: =D21*前提!$B$26 -> 19360 | I21: =H21*前提!$B$15/前提!$B$14 -> 774.4 | J21: =I21*前提!$B$5 -> 3717120 | K21: =I21*前提!$B$10-C21*前提!$B$22*前提!$B$7 -> 2287200 | L21: =F21+G21+J21 -> 22417120 | M21: =G21+K21+F21-C21*前提!$B$23 -> 20987200
A22: 12 | B22: =IF(A22<=12,1,IF(A22<=24,2,3)) -> 1 | C22: =IF(B22=1,前提!$B$27/12,IF(B22=2,前提!$B$28/12,前提!$B$29/12)) -> 20 | D22: =D21+C22 -> 240 | E22: =D22 -> 240 | F22: =C22*前提!$B$19 -> 6600000 | G22: =E22*前提!$B$20 -> 13200000 | H22: =D22*前提!$B$26 -> 21120 | I22: =H22*前提!$B$15/前提!$B$14 -> 844.8 | J22: =I22*前提!$B$5 -> 4055040 | K22: =I22*前提!$B$10-C22*前提!$B$22*前提!$B$7 -> 2498400 | L22: =F22+G22+J22 -> 23855040 | M22: =G22+K22+F22-C22*前提!$B$23 -> 22298400
A23: 13 | B23: =IF(A23<=12,1,IF(A23<=24,2,3)) -> 2 | C23: =IF(B23=1,前提!$B$27/12,IF(B23=2,前提!$B$28/12,前提!$B$29/12)) -> 30 | D23: =D22+C23 -> 270 | E23: =D23 -> 270 | F23: =C23*前提!$B$19 -> 9900000 | G23: =E23*前提!$B$20 -> 14850000 | H23: =D23*前提!$B$26 -> 23760 | I23: =H23*前提!$B$15/前提!$B$14 -> 950.4 | J23: =I23*前提!$B$5 -> 4561920 | K23: =I23*前提!$B$10-C23*前提!$B$22*前提!$B$7 -> 2797200 | L23: =F23+G23+J23 -> 29311920 | M23: =G23+K23+F23-C23*前提!$B$23 -> 27547200
... A46: 36 | B46: =IF(A46<=12,1,IF(A46<=24,2,3)) -> 3 | C46: =IF(B46=1,前提!$B$27/12,IF(B46=2,前提!$B$28/12,前提!$B$29/12)) -> 33.333333 | D46: =D45+C46 -> 1000 | E46: =D46 -> 1000 | F46: =C46*前提!$B$19 -> 11000000 | G46: =E46*前提!$B$20 -> 55000000 | H46: =D46*前提!$B$26 -> 88000 | I46: =H46*前提!$B$15/前提!$B$14 -> 3520 | J46: =I46*前提!$B$5 -> 16896000 | K46: =I46*前提!$B$10-C46*前提!$B$22*前提!$B$7 -> 10500000 | L46: =F46+G46+J46 -> 82896000 | M46: =G46+K46+F46-C46*前提!$B$23 -> 76500000
A48: ※リースは契約時（1カ月目）から課金＝課金台数は累計台数。初期費用¥330,000は別途の導入費（設置/初期設定/研修）。一括¥1,980,000／リース3年総額¥2,310,000（一括+17%・保守込み）。
A49: ※ジェル粗利(純)＝消費本数×粗利−無償提供(新規×原価)。ToB粗利＝リース売上＋ジェル粗利＋初期費用−機械原価。固定費控除前。解約なし仮定。
