Workbook

Sheet 前提
A1: VISUAL LABO｜専用ジェル経済性シミュレーション
A2: 青字＝入力・レバー（変更するとモデル全体が再計算されます）／黄色＝主要レバー
A4: ◤ 単価・原価（粗利は税抜同士で計算）
A5: ジェル卸価格（税抜） | B5: 4800 | C5: サロンへの卸単価。基準
A6: ジェル卸価格（税込10%） | B6: =B5*1.1 -> 5280 | C6: 税抜×1.1（＝¥5,280）
A7: OEM原価・1,000本ロット（税抜） | B7: 1800 | C7: 大量発注時の仕入原価
A8: OEM原価・500本ロット（税抜/参考） | B8: 2100 | C8: 小ロット時の仕入原価
A9: 採用原価（大量発注＝1,000本ロット） | B9: =B7 -> 1800
A10: 粗利／本（税抜） | B10: =B5-B9 -> 3000
A11: 粗利率 | B11: =B10/B5 -> 0.625
A13: ◤ 消費前提
A14: 1本あたり容量（ml） | B14: 750 | C14: 750〜800ml。控えめに750で試算
A15: 1施術あたり使用量（ml） | B15: 30 | C15: 60分施術で約30ml
A16: 1本あたり施術回数 | B16: =B14/B15 -> 25 | C16: 容量÷使用量（＝25回）
A18: ◤ 導入前提
A19: 年間導入目標（台/年） | B19: 300 | C19: 目標
A20: 月次導入ペース（台/月） | B20: =B19/12 -> 25 | C20: 300÷12（＝25台/月）
A21: 機械リース（円/月/台・参考） | B21: 55000 | C21: 6カ月後〜の月額課金。ToB継続の参考値
A23: 採用稼働（施術回数/月/台） | B23: 88 | C23: 3年試算に使用。標準=88（4回/日×22日）。控えめ=44／高稼働=200に変更可
A26: ◤ 稼働シナリオ（1台あたり月次・年次）
A27: シナリオ | B27: 回/日 | C27: 稼働日/月 | D27: 施術回数/月 | E27: 消費本数/月 | F27: ジェル売上/月(税抜) | G27: ジェル粗利/月 | H27: 年間ジェル粗利/台
A28: 控えめ | B28: 2 | C28: 22 | D28: =B28*C28 -> 44 | E28: =D28*$B$15/$B$14 -> 1.76 | F28: =E28*$B$5 -> 8448 | G28: =E28*$B$10 -> 5280 | H28: =G28*12 -> 63360
A29: 標準（採用） | B29: 4 | C29: 22 | D29: =B29*C29 -> 88 | E29: =D29*$B$15/$B$14 -> 3.52 | F29: =E29*$B$5 -> 16896 | G29: =E29*$B$10 -> 10560 | H29: =G29*12 -> 126720
A30: 高稼働 | B30: 8 | C30: 25 | D30: =B30*C30 -> 200 | E30: =D30*$B$15/$B$14 -> 8 | F30: =E30*$B$5 -> 38400 | G30: =E30*$B$10 -> 24000 | H30: =G30*12 -> 288000
A32: ※粗利は税抜（消費税は預り／仕払いで相殺のため）。原価は大量発注（1,000本ロット）を採用。

Sheet シミュレーション
A1: 全体シミュレーション（300台目標）
A2: 前提シートの値を変えると自動再計算されます。
A4: ◤ A. 300台フル稼働時の年間ランレート（シナリオ別）
A6: シナリオ | B6: 導入台数 | C6: 消費本数/月 | D6: ジェル売上/月 | E6: ジェル粗利/月 | F6: ジェル売上/年 | G6: ジェル粗利/年 | H6: 機械リース/年(参考) | I6: ToB継続/年(粗利+リース)
A7: 控えめ | B7: =前提!$B$19 -> 300 | C7: =$B7*前提!E28 -> 528 | D7: =$B7*前提!F28 -> 2534400 | E7: =$B7*前提!G28 -> 1584000 | F7: =D7*12 -> 30412800 | G7: =E7*12 -> 19008000 | H7: =$B7*前提!$B$21*12 -> 198000000 | I7: =G7+H7 -> 217008000
A8: 標準 | B8: =前提!$B$19 -> 300 | C8: =$B8*前提!E29 -> 1056 | D8: =$B8*前提!F29 -> 5068800 | E8: =$B8*前提!G29 -> 3168000 | F8: =D8*12 -> 60825600 | G8: =E8*12 -> 38016000 | H8: =$B8*前提!$B$21*12 -> 198000000 | I8: =G8+H8 -> 236016000
A9: 高稼働 | B9: =前提!$B$19 -> 300 | C9: =$B9*前提!E30 -> 2400 | D9: =$B9*前提!F30 -> 11520000 | E9: =$B9*前提!G30 -> 7200000 | F9: =D9*12 -> 138240000 | G9: =E9*12 -> 86400000 | H9: =$B9*前提!$B$21*12 -> 198000000 | I9: =G9+H9 -> 284400000
A11: ※フル稼働＝300台が全て稼働している定常状態（導入完了後）の年換算。リースは全台が月額(¥55,000)前提。
A14: ◤ B. 3年 継続収益シミュレーション（月25台導入・採用稼働）
B16: 期末累計台数 | C16: ジェル売上 | D16: ジェル粗利 | E16: 機械リース | F16: ToB継続計(粗利+リース)
A17: 1年目 | B17: =C33 -> 300 | C17: =SUM(F22:F33) -> 32947200 | D17: =SUM(G22:G33) -> 20592000 | E17: =SUM(H22:H33) -> 107250000 | F17: =SUM(I22:I33) -> 127842000
A18: 2年目 | B18: =C45 -> 600 | C18: =SUM(F34:F45) -> 93772800 | D18: =SUM(G34:G45) -> 58608000 | E18: =SUM(H34:H45) -> 305250000 | F18: =SUM(I34:I45) -> 363858000
A19: 3年目 | B19: =C57 -> 900 | C19: =SUM(F46:F57) -> 154598400 | D19: =SUM(G46:G57) -> 96624000 | E19: =SUM(H46:H57) -> 503250000 | F19: =SUM(I46:I57) -> 599874000
A20: ※月25台を3年継続導入し全台が稼働・継続（解約なし）と仮定。実際は解約率・稼働率で変動。
A21: 月 | B21: 新規導入 | C21: 累計台数 | D21: 施術回数/月 | E21: 消費本数/月 | F21: ジェル売上(税抜) | G21: ジェル粗利 | H21: 機械リース | I21: ToB継続計
A22: 1 | B22: =前提!$B$20 -> 25 | C22: =B22 -> 25 | D22: =C22*前提!$B$23 -> 2200 | E22: =D22*前提!$B$15/前提!$B$14 -> 88 | F22: =E22*前提!$B$5 -> 422400 | G22: =E22*前提!$B$10 -> 264000 | H22: =C22*前提!$B$21 -> 1375000 | I22: =G22+H22 -> 1639000
A23: 2 | B23: =前提!$B$20 -> 25 | C23: =C22+B23 -> 50 | D23: =C23*前提!$B$23 -> 4400 | E23: =D23*前提!$B$15/前提!$B$14 -> 176 | F23: =E23*前提!$B$5 -> 844800 | G23: =E23*前提!$B$10 -> 528000 | H23: =C23*前提!$B$21 -> 2750000 | I23: =G23+H23 -> 3278000
A24: 3 | B24: =前提!$B$20 -> 25 | C24: =C23+B24 -> 75 | D24: =C24*前提!$B$23 -> 6600 | E24: =D24*前提!$B$15/前提!$B$14 -> 264 | F24: =E24*前提!$B$5 -> 1267200 | G24: =E24*前提!$B$10 -> 792000 | H24: =C24*前提!$B$21 -> 4125000 | I24: =G24+H24 -> 4917000
A25: 4 | B25: =前提!$B$20 -> 25 | C25: =C24+B25 -> 100 | D25: =C25*前提!$B$23 -> 8800 | E25: =D25*前提!$B$15/前提!$B$14 -> 352 | F25: =E25*前提!$B$5 -> 1689600 | G25: =E25*前提!$B$10 -> 1056000 | H25: =C25*前提!$B$21 -> 5500000 | I25: =G25+H25 -> 6556000
A26: 5 | B26: =前提!$B$20 -> 25 | C26: =C25+B26 -> 125 | D26: =C26*前提!$B$23 -> 11000 | E26: =D26*前提!$B$15/前提!$B$14 -> 440 | F26: =E26*前提!$B$5 -> 2112000 | G26: =E26*前提!$B$10 -> 1320000 | H26: =C26*前提!$B$21 -> 6875000 | I26: =G26+H26 -> 8195000
A27: 6 | B27: =前提!$B$20 -> 25 | C27: =C26+B27 -> 150 | D27: =C27*前提!$B$23 -> 13200 | E27: =D27*前提!$B$15/前提!$B$14 -> 528 | F27: =E27*前提!$B$5 -> 2534400 | G27: =E27*前提!$B$10 -> 1584000 | H27: =C27*前提!$B$21 -> 8250000 | I27: =G27+H27 -> 9834000
A28: 7 | B28: =前提!$B$20 -> 25 | C28: =C27+B28 -> 175 | D28: =C28*前提!$B$23 -> 15400 | E28: =D28*前提!$B$15/前提!$B$14 -> 616 | F28: =E28*前提!$B$5 -> 2956800 | G28: =E28*前提!$B$10 -> 1848000 | H28: =C28*前提!$B$21 -> 9625000 | I28: =G28+H28 -> 11473000
A29: 8 | B29: =前提!$B$20 -> 25 | C29: =C28+B29 -> 200 | D29: =C29*前提!$B$23 -> 17600 | E29: =D29*前提!$B$15/前提!$B$14 -> 704 | F29: =E29*前提!$B$5 -> 3379200 | G29: =E29*前提!$B$10 -> 2112000 | H29: =C29*前提!$B$21 -> 11000000 | I29: =G29+H29 -> 13112000
A30: 9 | B30: =前提!$B$20 -> 25 | C30: =C29+B30 -> 225 | D30: =C30*前提!$B$23 -> 19800 | E30: =D30*前提!$B$15/前提!$B$14 -> 792 | F30: =E30*前提!$B$5 -> 3801600 | G30: =E30*前提!$B$10 -> 2376000 | H30: =C30*前提!$B$21 -> 12375000 | I30: =G30+H30 -> 14751000
A31: 10 | B31: =前提!$B$20 -> 25 | C31: =C30+B31 -> 250 | D31: =C31*前提!$B$23 -> 22000 | E31: =D31*前提!$B$15/前提!$B$14 -> 880 | F31: =E31*前提!$B$5 -> 4224000 | G31: =E31*前提!$B$10 -> 2640000 | H31: =C31*前提!$B$21 -> 13750000 | I31: =G31+H31 -> 16390000
A32: 11 | B32: =前提!$B$20 -> 25 | C32: =C31+B32 -> 275 | D32: =C32*前提!$B$23 -> 24200 | E32: =D32*前提!$B$15/前提!$B$14 -> 968 | F32: =E32*前提!$B$5 -> 4646400 | G32: =E32*前提!$B$10 -> 2904000 | H32: =C32*前提!$B$21 -> 15125000 | I32: =G32+H32 -> 18029000
A33: 12 | B33: =前提!$B$20 -> 25 | C33: =C32+B33 -> 300 | D33: =C33*前提!$B$23 -> 26400 | E33: =D33*前提!$B$15/前提!$B$14 -> 1056 | F33: =E33*前提!$B$5 -> 5068800 | G33: =E33*前提!$B$10 -> 3168000 | H33: =C33*前提!$B$21 -> 16500000 | I33: =G33+H33 -> 19668000
A34: 13 | B34: =前提!$B$20 -> 25 | C34: =C33+B34 -> 325 | D34: =C34*前提!$B$23 -> 28600 | E34: =D34*前提!$B$15/前提!$B$14 -> 1144 | F34: =E34*前提!$B$5 -> 5491200 | G34: =E34*前提!$B$10 -> 3432000 | H34: =C34*前提!$B$21 -> 17875000 | I34: =G34+H34 -> 21307000
... A57: 36 | B57: =前提!$B$20 -> 25 | C57: =C56+B57 -> 900 | D57: =C57*前提!$B$23 -> 79200 | E57: =D57*前提!$B$15/前提!$B$14 -> 3168 | F57: =E57*前提!$B$5 -> 15206400 | G57: =E57*前提!$B$10 -> 9504000 | H57: =C57*前提!$B$21 -> 49500000 | I57: =G57+H57 -> 59004000
